ramix/__init__.py
ramix/data_loader.py
ramix/mixture_maker.py
ramix/noise_maker.py
ramix/noisy_spectrum_maker.py
ramix/peak_funs.py
ramix/peak_skeleton.py
ramix/spectrum_skeleton.py
ramix-1.0.0.dist-info/LICENSE
ramix-1.0.0.dist-info/METADATA
ramix-1.0.0.dist-info/WHEEL
ramix-1.0.0.dist-info/top_level.txt
ramix-1.0.0.dist-info/RECORD
